moduleweb
